lmql/__init__.py
lmql/cli.py
lmql/demo.py
lmql/http.py
lmql/version.py
lmql/algorithms/__init__.py
lmql/algorithms/cache.py
lmql/algorithms/functools.py
lmql/api/__init__.py
lmql/api/inspect.py
lmql/api/llm.py
lmql/api/queries.py
lmql/api/run.py
lmql/api/scoring.py
lmql/api/serve.py
lmql/api/warnings.py
lmql/language/__init__.py
lmql/language/compiler.py
lmql/language/fragment_parser.py
lmql/language/qstrings.py
lmql/language/validator.py
lmql/lib/__init__.py
lmql/lib/actions.py
lmql/lib/data.py
lmql/lib/types.py
lmql/lib/value.py
lmql/lib/chat/__init__.py
lmql/lib/chat/__main__.py
lmql/lib/chat/chatserver.py
lmql/lib/chat/output.py
lmql/lib/chat/assets/code.svg
lmql/lib/chat/assets/index.css
lmql/lib/chat/assets/index.html
lmql/lib/chat/assets/lmql.svg
lmql/lib/chat/assets/send.svg
lmql/lib/chat/assets/studio.css
lmql/lib/prompts/__init__.py
lmql/lib/prompts/inline_code.py
lmql/lib/prompts/inline_use.py
lmql/lib/prompts/wiki_prompt.py
lmql/models/__init__.py
lmql/models/aliases.py
lmql/models/model_info.py
lmql/models/lmtp/__init__.py
lmql/models/lmtp/errors.py
lmql/models/lmtp/lmtp_async.py
lmql/models/lmtp/lmtp_balance.py
lmql/models/lmtp/lmtp_client.py
lmql/models/lmtp/lmtp_dcinprocess.py
lmql/models/lmtp/lmtp_dcmodel.py
lmql/models/lmtp/lmtp_inference_server.py
lmql/models/lmtp/lmtp_langchain.py
lmql/models/lmtp/lmtp_layout.py
lmql/models/lmtp/lmtp_multiprocessing.py
lmql/models/lmtp/lmtp_programmatic_serve_example.py
lmql/models/lmtp/lmtp_replicate_client.py
lmql/models/lmtp/lmtp_scheduler.py
lmql/models/lmtp/lmtp_serve.py
lmql/models/lmtp/lmtp_threading.py
lmql/models/lmtp/utils.py
lmql/models/lmtp/backends/__init__.py
lmql/models/lmtp/backends/__main__.py
lmql/models/lmtp/backends/llama_cpp_model.py
lmql/models/lmtp/backends/lmtp_model.py
lmql/models/lmtp/backends/random_model.py
lmql/models/lmtp/backends/transformers_model.py
lmql/ops/__init__.py
lmql/ops/booleans.py
lmql/ops/follow_map.py
lmql/ops/inline_call.py
lmql/ops/max_token_hints.py
lmql-0.7.3.dist-info/LICENSE
lmql-0.7.3.dist-info/METADATA
lmql-0.7.3.dist-info/WHEEL
lmql-0.7.3.dist-info/entry_points.txt
lmql-0.7.3.dist-info/top_level.txt
lmql-0.7.3.dist-info/RECORD
