Metadata-Version: 2.1
Name: lmql
Version: 0.7.3
Summary: A query language for language models.
Home-page: https://lmql.ai
Author: Luca Beurer-Kellner, Marc Fischer, Martin Vechev
Author-email: hello@lmql.ai
Project-URL: Docs, https://docs.lmql.ai
Classifier: Programming Language :: Python :: 3
Classifier: Operating System :: OS Independent
Requires-Python: >=3.10
License-File: LICENSE
Requires-Dist: aiohttp <4.0.0
Requires-Dist: astunparse ==1.6.3
Requires-Dist: openai
Requires-Dist: termcolor
Requires-Dist: numpy
Requires-Dist: tiktoken
Provides-Extra: hf
Requires-Dist: accelerate ; extra == 'hf'
Requires-Dist: transformers >=4.28.1 ; extra == 'hf'
Provides-Extra: llama
Requires-Dist: llama-cpp-python ; extra == 'llama'
Provides-Extra: replicate
Requires-Dist: aiohttp-sse-client ; extra == 'replicate'
Requires-Dist: transformers >=4.28.1 ; extra == 'replicate'
Provides-Extra: tests
Requires-Dist: pytest ; extra == 'tests'
Requires-Dist: pytest-asyncio ; extra == 'tests'
